{
  "generated_at": "2026-05-24T09:04:44.817845+09:00",
  "channel_name": "스마트대디",
  "period_days": 7,
  "daily": [
    {
      "date": "2026-05-18",
      "views": 3246,
      "likes": 20,
      "comments": 1,
      "subscribers_net": 14,
      "watch_minutes": 5927,
      "avg_view_duration_sec": 118.0,
      "avg_view_percentage": 28.68
    },
    {
      "date": "2026-05-19",
      "views": 3448,
      "likes": 38,
      "comments": 2,
      "subscribers_net": 26,
      "watch_minutes": 6689,
      "avg_view_duration_sec": 124.0,
      "avg_view_percentage": 27.47
    },
    {
      "date": "2026-05-20",
      "views": 3600,
      "likes": 51,
      "comments": 2,
      "subscribers_net": 19,
      "watch_minutes": 7088,
      "avg_view_duration_sec": 127.0,
      "avg_view_percentage": 26.99
    },
    {
      "date": "2026-05-21",
      "views": 3214,
      "likes": 30,
      "comments": 3,
      "subscribers_net": 30,
      "watch_minutes": 6313,
      "avg_view_duration_sec": 125.0,
      "avg_view_percentage": 27.21
    }
  ],
  "video_stats": [
    {
      "video_id": "lfq_r6r_0XY",
      "views": 33710,
      "avg_view_percentage": 37.03,
      "avg_view_duration_sec": 121.0,
      "likes": 247,
      "comments": 1
    },
    {
      "video_id": "_nCg7mHl7Zk",
      "views": 28677,
      "avg_view_percentage": 32.92,
      "avg_view_duration_sec": 126.0,
      "likes": 675,
      "comments": 36
    },
    {
      "video_id": "PJvt7ev3j6k",
      "views": 18019,
      "avg_view_percentage": 89.88,
      "avg_view_duration_sec": 44.0,
      "likes": 142,
      "comments": 11
    },
    {
      "video_id": "Ts-9MMZzkhM",
      "views": 12018,
      "avg_view_percentage": 20.31,
      "avg_view_duration_sec": 174.0,
      "likes": 252,
      "comments": 18
    },
    {
      "video_id": "qyTUW0fqgzc",
      "views": 11083,
      "avg_view_percentage": 102.82,
      "avg_view_duration_sec": 48.0,
      "likes": 47,
      "comments": 2
    },
    {
      "video_id": "L0E9X0DzvWs",
      "views": 10048,
      "avg_view_percentage": 32.04,
      "avg_view_duration_sec": 121.0,
      "likes": 78,
      "comments": 3
    },
    {
      "video_id": "iVq4OkfJPo0",
      "views": 7013,
      "avg_view_percentage": 38.25,
      "avg_view_duration_sec": 123.0,
      "likes": 109,
      "comments": 2
    },
    {
      "video_id": "CZDDJHzpCdM",
      "views": 6064,
      "avg_view_percentage": 92.52,
      "avg_view_duration_sec": 13.0,
      "likes": 0,
      "comments": 0
    },
    {
      "video_id": "EbKWRA_N4Gs",
      "views": 3625,
      "avg_view_percentage": 40.65,
      "avg_view_duration_sec": 147.0,
      "likes": 39,
      "comments": 3
    },
    {
      "video_id": "LawKU0gGr2Q",
      "views": 3511,
      "avg_view_percentage": 46.01,
      "avg_view_duration_sec": 115.0,
      "likes": 34,
      "comments": 0
    }
  ],
  "yesterday": {
    "date": "2026-05-21",
    "views": 3214,
    "likes": 30,
    "comments": 3,
    "subscribers_net": 30,
    "watch_minutes": 6313,
    "avg_view_duration_sec": 125.0,
    "avg_view_percentage": 27.21,
    "engagement_rate": 0.0103
  },
  "avg_7d": {
    "views": 3377.0,
    "likes": 34.75,
    "comments": 2.0,
    "subscribers_net": 22.25,
    "avg_view_percentage": 27.59
  }
}